signposting/__init__.py
signposting/__main__.py
signposting/cli.py
signposting/htmllinks.py
signposting/linkheader.py
signposting/linkset.py
signposting/resolver.py
signposting/signpost.py
signposting-0.9.9.dist-info/LICENSE
signposting-0.9.9.dist-info/METADATA
signposting-0.9.9.dist-info/WHEEL
signposting-0.9.9.dist-info/entry_points.txt
signposting-0.9.9.dist-info/top_level.txt
signposting-0.9.9.dist-info/zip-safe
signposting-0.9.9.dist-info/RECORD
