Metadata-Version: 2.1
Name: signposting
Version: 0.9.9
Summary: Parse and navigate FAIR Signposting Link headers
Home-page: https://github.com/stain/signposting
Author: Stian Soiland-Reyes
Author-email: stain@apache.org
License: Apache License, version 2.0
Project-URL: webpage, https://github.com/stain/signposting
Project-URL: Documentation, https://signposting.readthedocs.io/en/latest/
Project-URL: Changelog, https://github.com/stain/signposting/blob/main/docs/CHANGELOG.rst
Project-URL: Issue Tracker, https://github.com/stain/signposting/issues
Project-URL: Discussion Forum, https://github.com/stain/signposting/discussions
Keywords: FAIR,signposting,linked data,DOI,HTTP,linkset
Classifier: Development Status :: 3 - Alpha
Classifier: Environment :: Web Environment
Classifier: License :: OSI Approved :: Apache Software License
Classifier: Intended Audience :: Science/Research
Classifier: Programming Language :: Python :: 3.7
Classifier: Programming Language :: Python :: 3.8
Classifier: Programming Language :: Python :: 3.9
Classifier: Programming Language :: Python :: 3.10
Classifier: Topic :: Internet :: WWW/HTTP
Classifier: Topic :: Scientific/Engineering
Requires-Python: >=3.7
License-File: LICENSE
Requires-Dist: beautifulsoup4>=4.10
Requires-Dist: httplink==0.2.0
Requires-Dist: rfc3987>=1.3.8
Requires-Dist: requests>=2.28.1
Provides-Extra: tests
Requires-Dist: types-requests>=2.28.1; extra == "tests"
Requires-Dist: types-beautifulsoup4>=4.10; extra == "tests"
Requires-Dist: requests-mock>=1.9.3; extra == "tests"
